{"stats":{"minecraft:mined":{"minecraft:oak_log":26,"minecraft:oak_leaves":11},"minecraft:used":{"minecraft:diamond_axe":37},"minecraft:picked_up":{"minecraft:diamond_axe":1,"minecraft:stick":2,"minecraft:oak_log":25},"minecraft:custom":{"minecraft:jump":16,"minecraft:time_since_rest":6892,"minecraft:leave_game":8,"minecraft:play_time":6892,"minecraft:sprint_one_cm":7213,"minecraft:time_since_death":6892,"minecraft:walk_one_cm":2112,"minecraft:total_world_time":6892,"minecraft:fly_one_cm":758}},"DataVersion":3463}